mrg32k3a/__init__.py
mrg32k3a/mrg32k3a.py
mrg32k3a/py.typed
mrg32k3a/python.py
mrg32k3a/rust.py
mrg32k3a-2.0.0.dist-info/METADATA
mrg32k3a-2.0.0.dist-info/WHEEL
mrg32k3a-2.0.0.dist-info/licenses/LICENSE
mrg32k3a-2.0.0.dist-info/RECORD
