Metadata-Version: 2.4
Name: mrg32k3a
Version: 2.0.0
Summary: A Python implementation of the mrg32k3a pseudo-random number generator.
Project-URL: Homepage, https://github.com/simopt-admin/mrg32k3a
Project-URL: Documentation, https://mrg32k3a.readthedocs.io/en/latest/
Author-email: David Eckman <eckman@tamu.edu>, Shane Henderson <sgh9@cornell.edu>, Sara Shashaani <sshasha2@ncsu.edu>, William Grochocinski <williamgrochocinski@gmail.com>
License: MIT License
License-File: LICENSE
Classifier: License :: OSI Approved :: MIT License
Classifier: Operating System :: OS Independent
Classifier: Programming Language :: Python :: 3
Requires-Python: >=3.11
Requires-Dist: numpy
Provides-Extra: rust
Requires-Dist: mrg32k3a-core>=0.1.0; extra == 'rust'
